README.md
setup.py
./CMakeLists.txt
./_snippets/snippet_dictionary.cpp
./_snippets/dloading/CMakeLists.txt
./_snippets/dloading/include/Shape.h
./_snippets/dloading/include/ShapeOgre.h
./_snippets/dloading/include/ShapeUnreal.h
./_snippets/dloading/src/Shape.cpp
./_snippets/dloading/src/ShapeOgre.cpp
./_snippets/dloading/src/ShapeUnreal.cpp
./_snippets/dloading/src/main.cpp
./_snippets/dloading/src/test_both.cpp
./_snippets/json/CMakeLists.txt
./_snippets/json/parsing.cpp
./_snippets/json/include/json.hpp
./examples/CMakeLists.txt
./examples/test_com_forces.cpp
./examples/test_kintree.cpp
./examples/test_kintree_mjcf.cpp
./examples/test_kintree_rlsim.cpp
./examples/test_kintree_rlsim_viz.cpp
./examples/test_kintree_urdf.cpp
./examples/test_kintree_urdf_mjcviz.cpp
./examples/test_kintree_urdf_viz.cpp
./examples/test_runtime.cpp
./examples/test_terrain_static.cpp
./examples/test_visualizer_custom.cpp
./examples/test_visualizer_mujoco.cpp
./examples/test_visualizer_only.cpp
./include/mujoco_agent_wrapper.h
./include/mujoco_common.h
./include/mujoco_config.h
./include/mujoco_simulation.h
./include/mujoco_terrain_wrapper.h
./include/mujoco_utils.h
./mujocoviz/CMakeLists.txt
./mujocoviz/include/mujocoviz_ui.h
./mujocoviz/include/mujocoviz_viz.h
./mujocoviz/src/mujocoviz_ui.cpp
./mujocoviz/src/mujocoviz_viz.cpp
./src/mujoco_agent_wrapper.cpp
./src/mujoco_simulation.cpp
./src/mujoco_terrain_wrapper.cpp
./src/mujoco_utils.cpp
./tysoc/CMakeLists.txt
./tysoc/ext/CMakeLists.txt
./tysoc/ext/cat1/CMakeLists.txt
./tysoc/ext/cat1/Common.h
./tysoc/ext/cat1/Config.h
./tysoc/ext/cat1/examples/CMakeLists.txt
./tysoc/ext/cat1/examples/sample1_window.cpp
./tysoc/ext/cat1/examples/sample2_meshes.cpp
./tysoc/ext/cat1/examples/sample3_assimp.cpp
./tysoc/ext/cat1/examples/sample4_perlin_and_skybox.cpp
./tysoc/ext/cat1/ext/stb/stb_image.h
./tysoc/ext/cat1/include/LApp.h
./tysoc/ext/cat1/include/LAssetsManager.h
./tysoc/ext/cat1/include/LCommon.h
./tysoc/ext/cat1/include/LCubeTexture.h
tysoc_mjc.egg-info/PKG-INFO
tysoc_mjc.egg-info/SOURCES.txt
tysoc_mjc.egg-info/dependency_links.txt
tysoc_mjc.egg-info/not-zip-safe
tysoc_mjc.egg-info/requires.txt
tysoc_mjc.egg-info/top_level.txt