Metadata-Version: 1.0
Name: tysoc-mjc
Version: 0.0.1
Summary: Core functionality for a backend-agnostic locomotion framework
Home-page: https://github.com/wpumacay/tysocCore
Author: Wilbert Santos Pumacay Huallpa
Author-email: wpumacay@gmail.com
License: MIT License
Keywords: locomotion control simulation
Platform: UNKNOWN
